krupy/__init__.py
krupy/__main__.py
krupy/cli.py
krupy/errors.py
krupy/main.py
krupy/questionary/__init__.py
krupy/questionary/constants.py
krupy/questionary/form.py
krupy/questionary/prompt.py
krupy/questionary/prompts/__init__.py
krupy/questionary/prompts/autocomplete.py
krupy/questionary/prompts/checkbox.py
krupy/questionary/prompts/common.py
krupy/questionary/prompts/confirm.py
krupy/questionary/prompts/password.py
krupy/questionary/prompts/path.py
krupy/questionary/prompts/press_any_key_to_continue.py
krupy/questionary/prompts/rawselect.py
krupy/questionary/prompts/select.py
krupy/questionary/prompts/text.py
krupy/questionary/py.typed
krupy/questionary/question.py
krupy/questionary/styles.py
krupy/questionary/utils.py
krupy/questionary/version.py
krupy/subproject.py
krupy/template.py
krupy/tools.py
krupy/types.py
krupy/user_data.py
krupy/vcs.py
krupy-2.0.0.dist-info/METADATA
krupy-2.0.0.dist-info/WHEEL
krupy-2.0.0.dist-info/entry_points.txt
krupy-2.0.0.dist-info/RECORD
