Metadata-Version: 2.1
Name: krupy
Version: 2.0.0
Summary: A library for rendering project templates.
Home-page: https://github.com/Krunal-Kevadiya/krupy
License: MIT
Author: Krunal Kevadiya
Author-email: kevadiyakrunal22@gmail.com
Requires-Python: >=3.8,<4.0
Classifier: Development Status :: 5 - Production/Stable
Classifier: Intended Audience :: Developers
Classifier: License :: OSI Approved :: MIT License
Classifier: Programming Language :: Python :: 3
Classifier: Programming Language :: Python :: 3.8
Classifier: Programming Language :: Python :: 3.9
Classifier: Programming Language :: Python :: 3.10
Classifier: Programming Language :: Python :: 3.11
Classifier: Programming Language :: Python :: 3.12
Requires-Dist: colorama (>=0.4.3)
Requires-Dist: decorator (>=5.1.1)
Requires-Dist: dunamai (>=1.7.0)
Requires-Dist: funcy (>=1.17)
Requires-Dist: jinja2 (>=3.1.1)
Requires-Dist: jinja2-ansible-filters (>=1.3.1)
Requires-Dist: packaging (>=23.0)
Requires-Dist: pathspec (>=0.9.0)
Requires-Dist: plumbum (>=1.6.9)
Requires-Dist: prompt_toolkit (>=2.0,<=3.0.36)
Requires-Dist: pydantic (>=2.4.2)
Requires-Dist: pygments (>=2.7.1)
Requires-Dist: pyyaml (>=5.3.1)
Requires-Dist: pyyaml-include (>=1.2)
Requires-Dist: typing-extensions (>=3.7.4,<5.0.0) ; python_version < "3.9"
Project-URL: Bug Tracker, https://github.com/Krunal-Kevadiya/krupy/issues
Project-URL: Repository, https://github.com/Krunal-Kevadiya/krupy.git
